CHANGELOG.txt
LICENSE.txt
MANIFEST.in
README.txt
setup.py
index/__init__.py
write_print.egg-info/PKG-INFO
write_print.egg-info/SOURCES.txt
write_print.egg-info/dependency_links.txt
write_print.egg-info/requires.txt
write_print.egg-info/top_level.txt