Metadata-Version: 1.1
Name: write-print
Version: 0.0.1
Summary: print() is now write()
Home-page: UNKNOWN
Author: Joshua Lowe
Author-email: quitlookinatmygoddangemail@gmail.com
License: MIT
Keywords: write,say,print
Platform: UNKNOWN
Classifier: Development Status :: 5 - Production/Stable
Classifier: Intended Audience :: Education
Classifier: Operating System :: Microsoft :: Windows :: Windows 10
Classifier: License :: OSI Approved :: MIT License
Classifier: Programming Language :: Python :: 3
